README.md
setup.cfg
setup.py
gg69_expeval/__init__.py
gg69_expeval/executor.py
gg69_expeval/expeval.py
gg69_expeval/expeval_std.py
gg69_expeval/miscellanea.py
gg69_expeval/tokenizer.py
gg69_expeval/tokenizer_fixer.py
gg69_expeval/gg69_shell/__init__.py
gg69_expeval/gg69_shell/__main__.py
gg69_expeval/gg69_shell/detector.py
gg69_expeval/gg69_shell/shell.py
gg69_expeval/gg69_shell/signal.py
gg69_expeval/gg69_shell/TODO/__init__.py
gg69_expeval/gg69_shell/TODO/args_integration.py
gg69_expeval/gg69_shell/TODO/options_config.py
gg69_super_calc_engine.egg-info/PKG-INFO
gg69_super_calc_engine.egg-info/SOURCES.txt
gg69_super_calc_engine.egg-info/dependency_links.txt
gg69_super_calc_engine.egg-info/requires.txt
gg69_super_calc_engine.egg-info/top_level.txt