Metadata-Version: 1.1
Name: gg69-super-calc-engine
Version: 2.2.3
Summary: One line calculator engine with example of wrapping his functional
Home-page: https://github.com/1Gregory/gg69-calc-engine.git
Author: Andreew Gregory
Author-email: grinadand@gmail.com
License: MIT
Download-URL: https://github.com/1Gregory/gg69-calc-engine/archive/2.2.3.tar.gz
Keywords: cool,calc,expeval,calculator,69
Platform: UNKNOWN
